napari_tracks_reader/__init__.py
napari_tracks_reader/_containers.py
napari_tracks_reader/_csv_io.py
napari_tracks_reader/_icy_io.py
napari_tracks_reader/_io.py
napari_tracks_reader/_isbi_io.py
napari_tracks_reader/_reader.py
napari_tracks_reader/_reader_function.py
napari_tracks_reader/_st_io.py
napari_tracks_reader/_trackmate_io.py
napari_tracks_reader/_version.py
napari_tracks_reader/_tests/__init__.py
napari_tracks_reader/_tests/test_reader.py
napari_tracks_reader-0.1.3.dist-info/LICENSE
napari_tracks_reader-0.1.3.dist-info/METADATA
napari_tracks_reader-0.1.3.dist-info/WHEEL
napari_tracks_reader-0.1.3.dist-info/entry_points.txt
napari_tracks_reader-0.1.3.dist-info/top_level.txt
napari_tracks_reader-0.1.3.dist-info/RECORD
