Metadata-Version: 2.1
Name: napari-tracks-reader
Version: 0.1.3
Summary: Read tracks from txt (xml, csv) files to napari
Home-page: https://github.com/sylvainprigent/napari-tracks-reader
Author: Sylvain Prigent
Author-email: sylvain.prigent@inria.fr
License: GNU GPL v3.0
Platform: UNKNOWN
Classifier: Development Status :: 4 - Beta
Classifier: Intended Audience :: Developers
Classifier: Framework :: napari
Classifier: Topic :: Software Development :: Testing
Classifier: Programming Language :: Python
Classifier: Programming Language :: Python :: 3
Classifier: Programming Language :: Python :: 3.7
Classifier: Programming Language :: Python :: 3.8
Classifier: Programming Language :: Python :: 3.9
Classifier: Operating System :: OS Independent
Classifier: License :: OSI Approved :: GNU General Public License v3 (GPLv3)
Requires-Python: >=3.6
License-File: LICENSE
Requires-Dist: napari-plugin-engine (>=0.1.4)
Requires-Dist: numpy
Requires-Dist: pandas (>=1.2.4)
